zhao/__init__.py
zhao/xin_audio.py
zhao/xin_email.py
zhao/xin_net.py
zhao/xin_os.py
zhao/xin_postgresql.py
zhao/xin_re.py
zhao/xin_sqlite.py
zhao/xin_api/__init__.py
zhao/xin_api/amazon_mws.py
zhao/xin_api/baiduyuyin.py
zhao/xin_api/miwifi.py
zhao-0.0.94.dist-info/DESCRIPTION.rst
zhao-0.0.94.dist-info/METADATA
zhao-0.0.94.dist-info/RECORD
zhao-0.0.94.dist-info/WHEEL
zhao-0.0.94.dist-info/metadata.json
zhao-0.0.94.dist-info/top_level.txt
