Metadata-Version: 2.0
Name: zhao
Version: 0.0.94
Summary: 老赵分享给所有 Python 爱好者的包包
Home-page: http://nixoahz.com
Author: Zhao Xin
Author-email: 7176466@qq.com
License: GNU General Public License v3 (GPLv3)
Keywords: python3 implementations
Platform: cross-platform
Classifier: Development Status :: 3 - Alpha
Classifier: Intended Audience :: Developers
Classifier: License :: OSI Approved :: GNU General Public License v3 (GPLv3)
Classifier: Natural Language :: Chinese (Simplified)
Classifier: Natural Language :: English
Classifier: Operating System :: OS Independent
Classifier: Programming Language :: Python :: 3
Classifier: Programming Language :: Python :: 3.5
Classifier: Programming Language :: Python :: Implementation
Classifier: Topic :: Software Development :: Libraries :: Python Modules
Requires-Python: >=3.5
Requires-Dist: requests (>=2.18.4)
